aerleon/__init__.py
adamant-0.0.0.dist-info/METADATA
adamant-0.0.0.dist-info/WHEEL
adamant-0.0.0.dist-info/top_level.txt
adamant-0.0.0.dist-info/RECORD
