Metadata-Version: 2.1
Name: adamant
Version: 0.0.0
Summary: A firewall generation tool
License: Apache License
Keywords: firewall,networking,security
Classifier: Development Status :: 5 - Production/Stable
Classifier: License :: OSI Approved :: Apache Software License
Classifier: Operating System :: OS Independent
Classifier: Programming Language :: Python :: 3
Classifier: Programming Language :: Python :: 3.6
Classifier: Topic :: Security
Classifier: Topic :: System :: Networking :: Firewalls
Requires-Python: >=3.6
